pyseleniumjs/__init__.py
pyseleniumjs/e2ejs.py
pyseleniumjs-1.1.1.dist-info/DESCRIPTION.rst
pyseleniumjs-1.1.1.dist-info/METADATA
pyseleniumjs-1.1.1.dist-info/RECORD
pyseleniumjs-1.1.1.dist-info/WHEEL
pyseleniumjs-1.1.1.dist-info/metadata.json
pyseleniumjs-1.1.1.dist-info/top_level.txt
