Metadata-Version: 2.0
Name: pyseleniumjs
Version: 1.1.1
Summary: Small library with javascript utilities for official Python selenium bindings.
Home-page: https://github.com/neetVeritas/pyselenium-js
Author: John Nolette
Author-email: john@neetgroup.net
License: Apache2
Platform: UNKNOWN
Classifier: Development Status :: 5 - Production/Stable
Classifier: Intended Audience :: Developers
Classifier: License :: OSI Approved :: Apache Software License
Classifier: Programming Language :: Python :: 2.7
